mcp_server_deep_research/__init__.py
mcp_server_deep_research/server.py
deep_research_ai-1.0.1.dist-info/METADATA
deep_research_ai-1.0.1.dist-info/WHEEL
deep_research_ai-1.0.1.dist-info/entry_points.txt
deep_research_ai-1.0.1.dist-info/licenses/LICENSE
deep_research_ai-1.0.1.dist-info/RECORD
